setup.py
ld_probability/Binomialdistribution.py
ld_probability/Gaussiandistribution.py
ld_probability/Generaldistribution.py
ld_probability/__init__.py
ld_probability.egg-info/PKG-INFO
ld_probability.egg-info/SOURCES.txt
ld_probability.egg-info/dependency_links.txt
ld_probability.egg-info/not-zip-safe
ld_probability.egg-info/top_level.txt