Metadata-Version: 1.0
Name: ld-probability
Version: 1.0
Summary: Gaussian and Binomial distributions
Home-page: UNKNOWN
Author: Lakpa Dindu
Author-email: lakpadindu@hotmail.com
License: UNKNOWN
Platform: UNKNOWN
